gitlab_bm/__init__.py
gitlab_bm/app_info.py
gitlab_bm/backup.py
gitlab_bm/config.py
gitlab_bm/decorators.py
gitlab_bm/logging_setup.py
gitlab_bm/main.py
gitlab_bm/s3_utils.py
gitlab_bm/slack.py
gitlab_bm-0.1.3.dist-info/LICENSE
gitlab_bm-0.1.3.dist-info/METADATA
gitlab_bm-0.1.3.dist-info/WHEEL
gitlab_bm-0.1.3.dist-info/entry_points.txt
gitlab_bm-0.1.3.dist-info/RECORD
