Metadata-Version: 2.1
Name: gitlab-bm
Version: 0.1.3
Summary: Schedule/Run Gitlab Backups
Home-page: https://github.com/CodeBleu/gitlab_bm
License: MIT
Author: Jason Hollis
Author-email: 400979+CodeBleu@users.noreply.github.com
Requires-Python: >=3.10,<4.0
Classifier: License :: OSI Approved :: MIT License
Classifier: Programming Language :: Python :: 3
Classifier: Programming Language :: Python :: 3.10
Classifier: Programming Language :: Python :: 3.11
Classifier: Programming Language :: Python :: 3.12
Requires-Dist: boto3 (>=1.34.36,<2.0.0)
Requires-Dist: pyyaml (>=6.0.1,<7.0.0)
Requires-Dist: slack-sdk (>=3.26.2,<4.0.0)
Requires-Dist: tomlkit (>=0.12.3,<0.13.0)
Requires-Dist: typer (>=0.9.0,<0.10.0)
